{
  "accessibilityScore": 86,
  "aria-allowed-role-1": {
    "title": "Uses ARIA roles on incompatible elements",
    "description": "Many HTML elements can only be assigned certain ARIA roles. Using ARIA roles where they are not allowed can interfere with the accessibility of the web page. [Learn more about ARIA roles](https://dequeuniversity.com/rules/axe/4.10/aria-allowed-role).",
    "items": [
      {
        "snippet": "<input type=\"checkbox\" id=\"main-menu-input\" class=\"toggle-list__checkbox\" role=\"button\" aria-haspopup=\"true\" aria-expanded=\"false\" aria-labelledby=\"mw-mf-main-menu-button\">",
        "selector": "header.header-container > div.minerva-header > nav.navigation-drawer > input#main-menu-input",
        "explanation": "Fix any of the following:\n  ARIA role button is not allowed for given element",
        "boundingRect": {
          "top": 67,
          "bottom": 80,
          "left": 456,
          "right": 469,
          "width": 13,
          "height": 13
        }
      }
    ]
  },
  "aria-valid-attr-value-2": {
    "title": "`[aria-*]` attributes do not have valid values",
    "description": "Assistive technologies, like screen readers, can't interpret ARIA attributes with invalid values. [Learn more about valid values for ARIA attributes](https://dequeuniversity.com/rules/axe/4.10/aria-valid-attr-value).",
    "items": [
      {
        "snippet": "<a id=\"ca-watch\" href=\"/en/wiki/index.php?title=Special:UserLogin&amp;returnto=How+to+Find+Florida+De…\" class=\"mw-ui-icon mw-ui-icon-element mw-ui-icon-wikimedia-star-base20 mw-ui-icon-…\" data-mw=\"interface\" data-event-name=\"menu.watch\" role=\"button\" aria-controls=\"mw-watchlink-notification\">",
        "selector": "nav.page-actions-menu > ul#page-actions > li#page-actions-watch > a#ca-watch",
        "explanation": "Fix all of the following:\n  Invalid ARIA attribute value: aria-controls=\"mw-watchlink-notification\"",
        "boundingRect": {
          "top": 198,
          "bottom": 244,
          "left": 1269,
          "right": 1373,
          "width": 103,
          "height": 46
        }
      }
    ]
  },
  "color-contrast-3": {
    "title": "Background and foreground colors do not have a sufficient contrast ratio.",
    "description": "Low-contrast text is difficult or impossible for many users to read. [Learn how to provide sufficient color contrast](https://dequeuniversity.com/rules/axe/4.10/color-contrast).",
    "items": [
      {
        "snippet": "<a id=\"\" href=\"\" class=\"mw-ui-icon mw-ui-icon-element mw-ui-icon-wikimedia-language-base20 mw-ui-b…\" data-mw=\"interface\" data-event-name=\"menu.languages\" role=\"button\">",
        "selector": "nav.page-actions-menu > ul#page-actions > li#language-selector > a.mw-ui-icon",
        "explanation": "Fix any of the following:\n  Element has insufficient color contrast of 1.45 (foreground color: #d4d6d7, background color: #ffffff, font size: 12.0pt (16px), font weight: normal). Expected contrast ratio of 4.5:1",
        "boundingRect": {
          "top": 198,
          "bottom": 244,
          "left": 448,
          "right": 580,
          "width": 132,
          "height": 46
        },
        "subItems": {
          "type": "subitems",
          "items": [
            {
              "relatedNode": {
                "type": "node",
                "lhId": "1-3-MAIN",
                "path": "1,HTML,1,BODY,1,DIV,0,DIV,2,MAIN",
                "selector": "body.mediawiki > div#mw-mf-viewport > div#mw-mf-page-center > main#content",
                "boundingRect": {
                  "top": 135,
                  "bottom": 3734,
                  "left": 0,
                  "right": 1905,
                  "width": 1905,
                  "height": 3599
                },
                "snippet": "<main id=\"content\" class=\"mw-body\">",
                "nodeLabel": "How to Find Florida Death Records\nLanguage\nDownload PDF\nWatch\nEdit\nUnited State…"
              }
            }
          ]
        }
      },
      {
        "snippet": "<a href=\"/en/wiki/How_to_Find_Florida_Death_Records#Deaths_before_1877\">",
        "selector": "li > span > b > a",
        "explanation": "Fix any of the following:\n  Element has insufficient color contrast of 3.91 (foreground color: #3366cc, background color: #dcdcdc, font size: 12.6pt (16.8px), font weight: bold). Expected contrast ratio of 4.5:1",
        "boundingRect": {
          "top": 376,
          "bottom": 397,
          "left": 801,
          "right": 988,
          "width": 186,
          "height": 21
        },
        "subItems": {
          "type": "subitems",
          "items": [
            {
              "relatedNode": {
                "type": "node",
                "lhId": "1-5-TD",
                "path": "1,HTML,1,BODY,1,DIV,0,DIV,2,MAIN,2,DIV,0,DIV,1,DIV,0,SECTION,0,DIV,0,DIV,2,TABLE,0,TBODY,0,TR,1,TD",
                "selector": "table > tbody > tr > td",
                "boundingRect": {
                  "top": 330,
                  "bottom": 464,
                  "left": 771,
                  "right": 1347,
                  "width": 576,
                  "height": 134
                },
                "snippet": "<td width=\"55%\" bgcolor=\"DC DC DC\" style=\"width: 300px;\">",
                "nodeLabel": "Choose a time period to search for your ancestor's death record:\n\nDeaths before…"
              }
            }
          ]
        }
      },
      {
        "snippet": "<a href=\"/en/wiki/How_to_Find_Florida_Death_Records#Deaths_between_1877_and_1939\">",
        "selector": "li > span > b > a",
        "explanation": "Fix any of the following:\n  Element has insufficient color contrast of 3.91 (foreground color: #3366cc, background color: #dcdcdc, font size: 12.6pt (16.8px), font weight: bold). Expected contrast ratio of 4.5:1",
        "boundingRect": {
          "top": 408,
          "bottom": 429,
          "left": 801,
          "right": 1102,
          "width": 300,
          "height": 21
        },
        "subItems": {
          "type": "subitems",
          "items": [
            {
              "relatedNode": {
                "type": "node",
                "lhId": "1-5-TD",
                "path": "1,HTML,1,BODY,1,DIV,0,DIV,2,MAIN,2,DIV,0,DIV,1,DIV,0,SECTION,0,DIV,0,DIV,2,TABLE,0,TBODY,0,TR,1,TD",
                "selector": "table > tbody > tr > td",
                "boundingRect": {
                  "top": 330,
                  "bottom": 464,
                  "left": 771,
                  "right": 1347,
                  "width": 576,
                  "height": 134
                },
                "snippet": "<td width=\"55%\" bgcolor=\"DC DC DC\" style=\"width: 300px;\">",
                "nodeLabel": "Choose a time period to search for your ancestor's death record:\n\nDeaths before…"
              }
            }
          ]
        }
      },
      {
        "snippet": "<a href=\"/en/wiki/How_to_Find_Florida_Death_Records#Deaths_after_1939\">",
        "selector": "li > span > b > a",
        "explanation": "Fix any of the following:\n  Element has insufficient color contrast of 3.91 (foreground color: #3366cc, background color: #dcdcdc, font size: 12.6pt (16.8px), font weight: bold). Expected contrast ratio of 4.5:1",
        "boundingRect": {
          "top": 440,
          "bottom": 461,
          "left": 801,
          "right": 972,
          "width": 171,
          "height": 21
        },
        "subItems": {
          "type": "subitems",
          "items": [
            {
              "relatedNode": {
                "type": "node",
                "lhId": "1-5-TD",
                "path": "1,HTML,1,BODY,1,DIV,0,DIV,2,MAIN,2,DIV,0,DIV,1,DIV,0,SECTION,0,DIV,0,DIV,2,TABLE,0,TBODY,0,TR,1,TD",
                "selector": "table > tbody > tr > td",
                "boundingRect": {
                  "top": 330,
                  "bottom": 464,
                  "left": 771,
                  "right": 1347,
                  "width": 576,
                  "height": 134
                },
                "snippet": "<td width=\"55%\" bgcolor=\"DC DC DC\" style=\"width: 300px;\">",
                "nodeLabel": "Choose a time period to search for your ancestor's death record:\n\nDeaths before…"
              }
            }
          ]
        }
      },
      {
        "snippet": "<span class=\"last-modified-bar__text modified-enhancement\">",
        "selector": "footer.mw-footer > a.last-modified-bar > div.post-content > span.last-modified-bar__text",
        "explanation": "Fix any of the following:\n  Element has insufficient color contrast of 3.81 (foreground color: #72777d, background color: #eaecf0, font size: 10.5pt (14px), font weight: normal). Expected contrast ratio of 4.5:1",
        "boundingRect": {
          "top": 3745,
          "bottom": 3768,
          "left": 484,
          "right": 1433,
          "width": 949,
          "height": 23
        },
        "subItems": {
          "type": "subitems",
          "items": [
            {
              "relatedNode": {
                "type": "node",
                "lhId": "1-9-DIV",
                "path": "1,HTML,1,BODY,1,DIV,0,DIV",
                "selector": "body.mediawiki > div#mw-mf-viewport > div#mw-mf-page-center",
                "boundingRect": {
                  "top": 61,
                  "bottom": 3965,
                  "left": 0,
                  "right": 1905,
                  "width": 1905,
                  "height": 3904
                },
                "snippet": "<div id=\"mw-mf-page-center\">",
                "nodeLabel": "Open main menu\nFamilySearch Wiki\nHow to Find Florida Death Records\nLanguage\nDow…"
              }
            }
          ]
        }
      }
    ]
  },
  "definition-list-4": {
    "title": "`<dl>`'s do not contain only properly-ordered `<dt>` and `<dd>` groups, `<script>`, `<template>` or `<div>` elements.",
    "description": "When definition lists are not properly marked up, screen readers may produce confusing or inaccurate output. [Learn how to structure definition lists correctly](https://dequeuniversity.com/rules/axe/4.10/definition-list).",
    "items": [
      {
        "snippet": "<dl>",
        "selector": "tbody > tr > td > dl",
        "explanation": "Fix all of the following:\n  When not empty, element does not have at least one <dt> element followed by at least one <dd> element",
        "boundingRect": {
          "top": 332,
          "bottom": 376,
          "left": 787,
          "right": 1345,
          "width": 558,
          "height": 44
        }
      },
      {
        "snippet": "<dl>",
        "selector": "tbody > tr > td > dl",
        "explanation": "Fix all of the following:\n  When not empty, element does not have at least one <dt> element followed by at least one <dd> element",
        "boundingRect": {
          "top": 376,
          "bottom": 462,
          "left": 787,
          "right": 1345,
          "width": 558,
          "height": 86
        }
      },
      {
        "snippet": "<dl>",
        "selector": "tbody > tr > td > dl",
        "explanation": "Fix all of the following:\n  When not empty, element does not have at least one <dt> element followed by at least one <dd> element",
        "boundingRect": {
          "top": 711,
          "bottom": 795,
          "left": 475,
          "right": 801,
          "width": 326,
          "height": 84
        }
      },
      {
        "snippet": "<dl>",
        "selector": "tbody > tr > td > dl",
        "explanation": "Fix all of the following:\n  When not empty, element does not have at least one <dt> element followed by at least one <dd> element",
        "boundingRect": {
          "top": 721,
          "bottom": 784,
          "left": 821,
          "right": 1147,
          "width": 326,
          "height": 63
        }
      },
      {
        "snippet": "<dl>",
        "selector": "section#mf-section-0 > div.mw-parser-output > div.mw-parser-output > dl",
        "explanation": "Fix all of the following:\n  When not empty, element does not have at least one <dt> element followed by at least one <dd> element",
        "boundingRect": {
          "top": 2754,
          "bottom": 2806,
          "left": 470,
          "right": 1450,
          "width": 979,
          "height": 52
        }
      },
      {
        "snippet": "<dl>",
        "selector": "section#mf-section-0 > div.mw-parser-output > div.mw-parser-output > dl",
        "explanation": "Fix all of the following:\n  When not empty, element does not have at least one <dt> element followed by at least one <dd> element",
        "boundingRect": {
          "top": 3046,
          "bottom": 3284,
          "left": 470,
          "right": 1450,
          "width": 979,
          "height": 238
        }
      }
    ]
  },
  "link-in-text-block-5": {
    "title": "Links rely on color to be distinguishable.",
    "description": "Low-contrast text is difficult or impossible for many users to read. Link text that is discernible improves the experience for users with low vision. [Learn how to make links distinguishable](https://dequeuniversity.com/rules/axe/4.10/link-in-text-block).",
    "items": [
      {
        "snippet": "<a href=\"/en/wiki/Substitute_Records_For_United_States_Death_Information\">",
        "selector": "div.mw-parser-output > div.mw-parser-output > p > a",
        "explanation": "Fix any of the following:\n  The link has insufficient color contrast of 2.35:1 with the surrounding text. (Minimum contrast is 3:1, link text: #3366cc, surrounding text: #333333)\n  The link has no styling (such as underline) to distinguish it from the surrounding text",
        "boundingRect": {
          "top": 625,
          "bottom": 642,
          "left": 1020,
          "right": 1147,
          "width": 127,
          "height": 17
        },
        "subItems": {
          "type": "subitems",
          "items": [
            {
              "relatedNode": {
                "type": "node",
                "lhId": "1-17-P",
                "path": "1,HTML,1,BODY,1,DIV,0,DIV,2,MAIN,2,DIV,0,DIV,1,DIV,0,SECTION,0,DIV,0,DIV,6,P",
                "selector": "section#mf-section-0 > div.mw-parser-output > div.mw-parser-output > p",
                "boundingRect": {
                  "top": 623,
                  "bottom": 665,
                  "left": 456,
                  "right": 1450,
                  "width": 993,
                  "height": 42
                },
                "snippet": "<p>",
                "nodeLabel": "Before 1877, no deaths were recorded by the county or state. You must search su…"
              }
            }
          ]
        }
      }
    ]
  },
  "table-fake-caption-6": {
    "title": "Tables do not use `<caption>` instead of cells with the `[colspan]` attribute to indicate a caption.",
    "description": "Screen readers have features to make navigating tables easier. Ensuring that tables use the actual caption element instead of cells with the `[colspan]` attribute may improve the experience for screen reader users. [Learn more about captions](https://dequeuniversity.com/rules/axe/4.10/table-fake-caption).",
    "items": [
      {
        "snippet": "<table width=\"70%\" border=\"1\" style=\"margin: 1em auto;\">",
        "selector": "section#mf-section-0 > div.mw-parser-output > div.mw-parser-output > table",
        "explanation": "Fix all of the following:\n  The first child of the table should be a caption instead of a table cell",
        "boundingRect": {
          "top": 679,
          "bottom": 800,
          "left": 456,
          "right": 1152,
          "width": 695,
          "height": 121
        }
      },
      {
        "snippet": "<table cellspacing=\"0\" class=\"nowraplinks collapsible autocollapse\" style=\"width:100%;margin-bottom: 0px; background:transparent; color:inherit;;\" id=\"collapsibleTable0\">",
        "selector": "tbody > tr > td > table#collapsibleTable0",
        "explanation": "Fix all of the following:\n  The first child of the table should be a caption instead of a table cell",
        "boundingRect": {
          "top": 3315,
          "bottom": 3684,
          "left": 459,
          "right": 1447,
          "width": 987,
          "height": 368
        }
      }
    ]
  },
  "td-has-header-7": {
    "title": "`<td>` elements in a large `<table>` do not have table headers.",
    "description": "Screen readers have features to make navigating tables easier. Ensuring that `<td>` elements in a large table (3 or more cells in width and height) have an associated table header may improve the experience for screen reader users. [Learn more about table headers](https://dequeuniversity.com/rules/axe/4.10/td-has-header).",
    "items": [
      {
        "snippet": "<table width=\"100%\" cellspacing=\"1\" cellpadding=\"6\" border=\"0\">",
        "selector": "section#mf-section-0 > div.mw-parser-output > div.mw-parser-output > table",
        "explanation": "Fix all of the following:\n  Some non-empty data cells do not have table headers",
        "boundingRect": {
          "top": 1119,
          "bottom": 1745,
          "left": 456,
          "right": 1450,
          "width": 993,
          "height": 626
        },
        "subItems": {
          "type": "subitems",
          "items": [
            {
              "relatedNode": {
                "type": "node",
                "lhId": "1-21-TD",
                "path": "1,HTML,1,BODY,1,DIV,0,DIV,2,MAIN,2,DIV,0,DIV,1,DIV,0,SECTION,0,DIV,0,DIV,15,TABLE,0,TBODY,0,TR,0,TD",
                "selector": "table > tbody > tr > td",
                "boundingRect": {
                  "top": 1120,
                  "bottom": 1153,
                  "left": 457,
                  "right": 1423,
                  "width": 965,
                  "height": 33
                },
                "snippet": "<td align=\"left\" colspan=\"3\">",
                "nodeLabel": "Florida Death Databases - Includes Indexes Only"
              }
            },
            {
              "relatedNode": {
                "type": "node",
                "lhId": "1-22-TD",
                "path": "1,HTML,1,BODY,1,DIV,0,DIV,2,MAIN,2,DIV,0,DIV,1,DIV,0,SECTION,0,DIV,0,DIV,15,TABLE,0,TBODY,1,TR,0,TD",
                "selector": "table > tbody > tr > td",
                "boundingRect": {
                  "top": 1154,
                  "bottom": 1187,
                  "left": 457,
                  "right": 532,
                  "width": 75,
                  "height": 33
                },
                "snippet": "<td>",
                "nodeLabel": "Try 1st:"
              }
            },
            {
              "relatedNode": {
                "type": "node",
                "lhId": "1-23-TD",
                "path": "1,HTML,1,BODY,1,DIV,0,DIV,2,MAIN,2,DIV,0,DIV,1,DIV,0,SECTION,0,DIV,0,DIV,15,TABLE,0,TBODY,2,TR,1,TD",
                "selector": "table > tbody > tr > td",
                "boundingRect": {
                  "top": 1188,
                  "bottom": 1263,
                  "left": 533,
                  "right": 780,
                  "width": 247,
                  "height": 75
                },
                "snippet": "<td width=\"25%\">",
                "nodeLabel": "1877-1939 - At FamilySearch.org"
              }
            }
          ]
        }
      }
    ]
  }
}